algebraic/__init__.py
algebraic/_jax_wrappers.py
algebraic/array/__init__.py
algebraic/array/_index_update.py
algebraic/array/core.py
algebraic/kernels/__init__.py
algebraic/numpy.py
algebraic/numpy.pyi
algebraic/polynomials/__init__.py
algebraic/polynomials/monomial_basis.py
algebraic/polynomials/rank_decomp.py
algebraic/polynomials/sparse.py
algebraic/py.typed
algebraic/semirings.py
algebraic/spec.py
algebraic_jax-1.0.0.dist-info/WHEEL
algebraic_jax-1.0.0.dist-info/METADATA
algebraic_jax-1.0.0.dist-info/RECORD
