Metadata-Version: 2.3
Name: algebraic-jax
Version: 1.0.0
Summary: Abstract algebric structures for GPU-efficient computation
Author: Anand Balakrishnan
Author-email: Anand Balakrishnan <anandbala1597@gmail.com>
Requires-Dist: jax>=0.8
Requires-Dist: jaxtyping>=0.3
Requires-Dist: equinox>=0.12
Requires-Dist: attrs>=25.4.0
Requires-Dist: opt-einsum>=3.4.0
Requires-Dist: bitarray>=3.0.0
Requires-Dist: optree>=0.18.0
Requires-Dist: quax>=0.2.1
Requires-Python: >=3.12
